imas_validator/__init__.py
imas_validator/__main__.py
imas_validator/_version.py
imas_validator/exceptions.py
imas_validator/setup_logging.py
imas_validator/validate_options.py
imas_validator/assets/rulesets/generic/__init__.py
imas_validator/assets/rulesets/generic/core_profiles.py
imas_validator/assets/rulesets/generic/core_sources.py
imas_validator/assets/rulesets/generic/core_transport.py
imas_validator/assets/rulesets/generic/edge_profiles.py
imas_validator/assets/rulesets/generic/edge_sources.py
imas_validator/assets/rulesets/generic/edge_transport.py
imas_validator/assets/rulesets/generic/generic.py
imas_validator/assets/rulesets/generic/pf_active.py
imas_validator/assets/rulesets/generic/plasma_profiles.py
imas_validator/assets/rulesets/generic/plasma_sources.py
imas_validator/assets/rulesets/generic/plasma_transport.py
imas_validator/assets/rulesets/generic/radiation.py
imas_validator/assets/rulesets/generic/summary.py
imas_validator/assets/rulesets/iter/__init__.py
imas_validator/assets/rulesets/iter/core_profiles.py
imas_validator/assets/rulesets/iter/edge_profiles.py
imas_validator/assets/rulesets/iter/equilibrium.py
imas_validator/assets/rulesets/iter/summary.py
imas_validator/assets/rulesets/scenarios/__init__.py
imas_validator/assets/rulesets/scenarios/core_profiles.py
imas_validator/assets/rulesets/scenarios/edge_profiles.py
imas_validator/assets/rulesets/scenarios/edge_sources.py
imas_validator/assets/rulesets/scenarios/edge_transport.py
imas_validator/assets/rulesets/scenarios/equilibrium.py
imas_validator/assets/rulesets/scenarios/summary.py
imas_validator/assets/training_rulesets/custom_ruleset/__init__.py
imas_validator/assets/training_rulesets/custom_ruleset/training_custom.py
imas_validator/cli/__init__.py
imas_validator/cli/command_parser.py
imas_validator/cli/imas_validator_cli.py
imas_validator/cli/commands/__init__.py
imas_validator/cli/commands/command_generic.py
imas_validator/cli/commands/command_interface.py
imas_validator-1.0.0.dist-info/licenses/LICENSE.txt
imas_validator-1.0.0.dist-info/METADATA
imas_validator-1.0.0.dist-info/WHEEL
imas_validator-1.0.0.dist-info/entry_points.txt
imas_validator-1.0.0.dist-info/top_level.txt
imas_validator-1.0.0.dist-info/RECORD
